robocrew/__init__.py
robocrew/core/LLMAgent.py
robocrew/core/memory.py
robocrew/core/sound_receiver.py
robocrew/core/tools.py
robocrew/core/utils.py
robocrew/robots/XLeRobot/DOC.md
robocrew/robots/XLeRobot/servo_controls.py
robocrew/robots/XLeRobot/tools.py
robocrew/scripts/robocrew_find_components.py
robocrew/scripts/robocrew_generate_udev_rules.py
robocrew-0.1.0.dist-info/METADATA
robocrew-0.1.0.dist-info/WHEEL
robocrew-0.1.0.dist-info/entry_points.txt
robocrew-0.1.0.dist-info/licenses/.github/LICENSE
robocrew-0.1.0.dist-info/RECORD
