Metadata-Version: 2.4
Name: robocrew
Version: 0.1.0
Summary: 🦾Set up your embodied LLM agent same easiness as you set up normal agents in CrewAI or Autogen
Project-URL: Homepage, https://github.com/Grigorij-Dudnik/RoboCrew
Author-email: Grigorij Dudnik <dudnikgrv@gmail.com>, Konrad Suchodolski <konrad.suchodolski50@gmail.com>
License-Expression: MIT
License-File: .github/LICENSE
Classifier: Operating System :: OS Independent
Classifier: Programming Language :: Python :: 3
Requires-Python: >=3.10
Requires-Dist: feetech-servo-sdk==1.0.0
Requires-Dist: google-ai-generativelanguage==0.9.0
Requires-Dist: grpcio==1.73.1
Requires-Dist: langchain-google-genai==3.2.0
Requires-Dist: langchain-openai==1.1.0
Requires-Dist: langchain==1.1.0
Requires-Dist: lerobot==0.4.2
Requires-Dist: lerobot[async]==0.4.2
Requires-Dist: openai==2.8.1
Requires-Dist: opencv-python==4.10.0.84
Requires-Dist: pyaudio==0.2.14
Requires-Dist: python-dotenv==1.2.1
Requires-Dist: pyttsx3
